Metadata-Version: 2.1
Name: gitchm
Version: 0.1.0
Summary: CLI tool that copies commit history without reproducing the working tree
Home-page: https://github.com/ralphqq/gitchm
Author: Ralph Quirequire
Author-email: ralph.quirequire2012@gmail.com
License: MIT License
Keywords: git commit history repo repository working tree directory mirror replicate replicator reproduce
Platform: UNKNOWN
Classifier: Development Status :: 5 - Production/Stable
Classifier: Environment :: Console
Classifier: Intended Audience :: Developers
Classifier: Programming Language :: Python :: 3.8
Classifier: Operating System :: POSIX
Requires-Python: >=3.8
Provides-Extra: tests
